{
  "type": "FeatureCollection",
  "features": [
    {
      "type": "Feature",
      "properties": {
        "Name": "Facultad de Ciencias",
        "description": "<div style=\"color:#9d0de5;font-weight:bold;\"><a href=\"http://t.ull.es/7hl\">Sitio Web</a><br><a href=\"\"></div>",
        "tessellate": -1,
        "extrude": 0,
        "visibility": -1,
        "Sitio_Web": "https://www.ull.es/centros/facultad-ciencias",
        "imagen": "http://www.periodismoull.es/wp-content/uploads/2017/09/1mates.jpg"
      },
      "geometry": {
        "type": "Point",
        "coordinates": [
          -16.320874,
          28.481717,
          0
        ]
      }
    },
    {
      "type": "Feature",
      "properties": {
        "Name": "Escuela Superior de Ingeniería y Tecnología",
        "imagen": "",
        "Latitud": 28.482938,
        "Longitud": -16.321789,
        "Galer__a_de_im__genes": "",
        "Sitio_Web": "http://t.ull.es/7ho",
        "imagen": "https://www.ull.es/portal/noticias/wp-content/uploads/sites/13/2017/05/Informatica_ing-civil.jpg"
      },
      "geometry": {
        "type": "Point",
        "coordinates": [
          -16.321789,
          28.482938,
          0
        ]
      }
    }
  ]
}